forkserver/__init__.py
forkserver/__main__.py
forkserver/lib/checkpoint.py
forkserver/lib/context.py
forkserver/lib/events.py
forkserver/lib/filename_to_module.py
forkserver/servers/coordinator.py
forkserver/servers/forkserver.py
forkserver/servers/http.py
forkserver/servers/watcher.py
forkserver-0.1.2.dist-info/METADATA
forkserver-0.1.2.dist-info/WHEEL
forkserver-0.1.2.dist-info/entry_points.txt
forkserver-0.1.2.dist-info/RECORD
